[
  {
    "id": "41d260d7-7d29-46d6-a54b-c2758db3bf55",
    "type": "commitless",
    "name": "chore(Installation environnement GitHub)",
    "description": "Installation et mise en place de l'environnement de travail, aide de mon professeur concernant le fonctionnement des programmes.\r\nexplication concernant les objectif du projet",
    "date": "2025-11-14T12:35",
    "duration": 45,
    "status": "Done",
    "author": "?"
  },
  {
    "id": "c3f8b0b3-3357-4130-93fb-044cc46d2dc4",
    "type": "commitless",
    "name": "Maladie",
    "description": "Maladie",
    "date": "2025-11-07T12:20",
    "duration": 225,
    "status": "Done",
    "author": "?"
  },
  {
    "id": "0712a52d-00ef-444b-9067-bd810f0fcac3",
    "type": "commitless",
    "name": "chore(Explication recues Javascript)",
    "description": "Explication concernant les test et de la commande npm run test",
    "date": "2025-11-14T13:20",
    "duration": 20,
    "status": "Done",
    "author": "?"
  },
  {
    "id": "fee1f6d4-fb55-4df8-90d0-053e64b4ed26",
    "type": "commitless",
    "name": "feat(HelloWord)",
    "description": "1er exercice",
    "date": "2025-11-14T13:40",
    "duration": 10,
    "status": "Done",
    "author": "?"
  },
  {
    "id": "41f59068-024f-4b2d-9805-441f419e97be",
    "type": "commitless",
    "name": "feat(lasagna)",
    "description": "test pas passée 2 fois. Reussi la 3ème fois",
    "date": "2025-11-14T13:50",
    "duration": 50,
    "status": "Done",
    "author": "?"
  },
  {
    "id": "f79f205b-ea67-4e4a-99e6-bcf58976bfaa",
    "type": "commitless",
    "name": "feat(annalyns-infiltration)",
    "description": "test reussi après environ 10 correction de code.",
    "date": "2025-11-14T15:00",
    "duration": 60,
    "status": "Done",
    "author": "?"
  },
  {
    "id": "507137f8-226f-48ac-b430-824746bb7817",
    "type": "commitless",
    "name": "feat(freelancer-rates)",
    "description": "environ 12 test avant de pouvoir valider le code",
    "date": "2025-11-14T15:50",
    "duration": 50,
    "status": "Done",
    "author": "?"
  },
  {
    "id": "2ea087b3-65a9-4e01-9746-2f31e3e1d95d",
    "type": "commitless",
    "name": "feat(annalyns-infiltration)",
    "description": "Retour de mon professeur concernant l'exercice annalyns-infiltration\r\nil faut simplifier le code, éviter la redondance et ne pas écrire des lignes qui disent la même chose que cela fait déjà",
    "date": "2025-11-14T16:10",
    "duration": 0,
    "status": "Done",
    "author": "?"
  },
  {
    "id": "b810b62b-dd44-4930-a5dd-7f283ce5997c",
    "type": "commitless",
    "name": "chore(test theorique)",
    "description": "resultat : 5.2",
    "date": "2025-12-12T12:32",
    "duration": 30,
    "status": "Done",
    "author": "?"
  },
  {
    "id": "03a9a70f-6951-4fc6-8e07-be70c059c99e",
    "type": "commitless",
    "name": "feat(bird watcher)",
    "description": "teste passé, exercice terminé",
    "date": "2025-12-12T11:23",
    "duration": 75,
    "status": "Done",
    "author": "?"
  },
  {
    "id": "3a364e31-d4e3-460b-a8a7-8d55c347a367",
    "type": "commitless",
    "name": "feat(bob)",
    "description": "exercice retravaillé mais toujours en cours",
    "date": "2025-12-12T11:25",
    "duration": 25,
    "status": "Done",
    "author": "?"
  },
  {
    "id": "1088a345-bb7f-4d9e-9879-957437ebc498",
    "type": "commitless",
    "name": "chore(mise en forme de document)",
    "description": "problème avec la mise en forme dans mes code, explication recue",
    "date": "2025-12-12T11:26",
    "duration": 15,
    "status": "Done",
    "author": "?"
  },
  {
    "id": "fbe62491-de08-4671-8ba7-961b0cf8f390",
    "type": "commitless",
    "name": "feat(fruit picker)",
    "description": "exercice terminé",
    "date": "2025-11-28T11:27",
    "duration": 55,
    "status": "Done",
    "author": "?"
  },
  {
    "id": "4fc40884-bc91-4e0f-b1f7-1e78881420be",
    "type": "commitless",
    "name": "feat(giga seconde)",
    "description": "exercice terminé",
    "date": "2025-11-28T11:28",
    "duration": 85,
    "status": "Done",
    "author": "?"
  },
  {
    "id": "5a4e8e20-ce3f-4d3f-8741-9bc88ea57e76",
    "type": "commitless",
    "name": "feat(captains-log)",
    "description": "exercice terminé",
    "date": "2025-11-28T11:29",
    "duration": 65,
    "status": "Done",
    "author": "?"
  },
  {
    "id": "a806eacd-7481-4cb2-8481-a3146edb98be",
    "type": "commitless",
    "name": "feat(space-age)",
    "description": "notions de ms dans js",
    "date": "2025-11-28T11:29",
    "duration": 70,
    "status": "Done",
    "author": "?"
  },
  {
    "id": "22af1dcb-7635-469a-a88f-a8d12746a09d",
    "type": "commitless",
    "name": "feat(bank-account)",
    "description": "exercice fini de la session précédente",
    "date": "2025-11-28T11:30",
    "duration": 35,
    "status": "Done",
    "author": "?"
  },
  {
    "id": "07ae229a-05f1-494c-947d-cb23639c5d6b",
    "type": "commitless",
    "name": "feat(bob)",
    "description": "je bloque sur ce code,je crois que je fais trop de vérification, regEx me semble juste pourtant",
    "date": "2025-12-21T11:31",
    "duration": 40,
    "status": "Done",
    "author": "?"
  },
  {
    "id": "e95b2a00-a017-4c0a-8745-22c2de32c41e",
    "type": "commitless",
    "name": "feat(Lucky numbers)",
    "description": "appris a séparer une chaine avec split , inversé avec reverse et assembler avec join",
    "date": "2025-12-21T11:32",
    "duration": 80,
    "status": "Done",
    "author": "?"
  },
  {
    "id": "d553484f-91db-49a0-ae4b-a70ad4cb356b",
    "type": "commitless",
    "name": "feat(resistor color)",
    "description": "travail avec indexOf",
    "date": "2025-12-21T11:33",
    "duration": 80,
    "status": "Done",
    "author": "?"
  },
  {
    "id": "c5897756-cdc0-427e-a464-0bf6b52726f0",
    "type": "commitless",
    "name": "feat(Two fer)",
    "description": "essayé d'utilisé ${name || \"you\"} mais les test chez moi ne passait pas",
    "date": "2025-12-22T11:33",
    "duration": 90,
    "status": "Done",
    "author": "?"
  },
  {
    "id": "56b5751c-c37d-44cd-a4f4-774cf28c0571",
    "type": "commitless",
    "name": "feat(vehicle purchase)",
    "description": "localCompare va tenir compte de l'alphabet de l ordinateur local et  va supprimer les accent par exemple.\r\nJe n'arrivais pas a passer les test sans utiliser cela, j'ai cru avoir compris comment l utiliser mais je n'ai pas saisi la notion alphabétique",
    "date": "2025-12-22T11:34",
    "duration": 95,
    "status": "Done",
    "author": "?"
  },
  {
    "id": "2c67b830-d5a3-409a-bd91-70e553308528",
    "type": "commitless",
    "name": "feat(nullability)",
    "description": "transformer id en chaine de char ave + id +",
    "date": "2025-12-28T13:29",
    "duration": 75,
    "status": "Done",
    "author": "?"
  },
  {
    "id": "73e5db5e-d17a-46a8-92ba-4c4ffb522039",
    "type": "commitless",
    "name": "feat(mixed juice)",
    "description": "",
    "date": "2025-12-28T13:33",
    "duration": 65,
    "status": "Done",
    "author": "?"
  },
  {
    "id": "e17029b7-3e09-4bc2-8513-a82a79b07b6d",
    "type": "commitless",
    "name": "feat(elysee destructed enchantement)",
    "description": "travail avec la destructuration",
    "date": "2025-12-29T13:46",
    "duration": 90,
    "status": "Done",
    "author": "?"
  },
  {
    "id": "a3077ec5-2a33-4821-9771-f4ac0f280294",
    "type": "commitless",
    "name": "feat(elysee analytic enchantement)",
    "description": "notion de reste de division % 2, travail avec some, find, findIndex pour retourner des cartes précise",
    "date": "2025-12-29T13:50",
    "duration": 105,
    "status": "Done",
    "author": "?"
  },
  {
    "id": "4392a309-58b7-44d7-8967-c21810b5d891",
    "type": "commitless",
    "name": "chore(push, résolution de conflit)",
    "description": "[done]\r\n[problème rencontré]",
    "date": "2026-01-09T13:11",
    "duration": 25,
    "status": "Done",
    "author": "?"
  },
  {
    "id": "8951c76d-caf3-4202-b799-1728948bac92",
    "type": "commitpatch",
    "sha": "5e930eb038e34068794e65342dd48a21ade34e04",
    "url": "https://github.com/hellokimmydream/p-bulle-exercices-js-start/commit/5e930eb038e34068794e65342dd48a21ade34e04",
    "name": "chore(jdt)",
    "description": "installation",
    "date": "2025-11-21T11:58:00.000Z",
    "duration": 15,
    "status": "Done",
    "author": "hellokimmydream",
    "patch": true
  },
  {
    "id": "0206f3b5-0b89-4de8-bf73-ab0c9bd5f244",
    "type": "commitpatch",
    "sha": "920bf716f10cbd4615fa253169b0f4d27bf712b4",
    "url": "https://github.com/hellokimmydream/p-bulle-exercices-js-start/commit/920bf716f10cbd4615fa253169b0f4d27bf712b4",
    "name": "feat(annalyns-infiltration)",
    "description": "correction exercice",
    "date": "2025-11-21T12:43:00.000Z",
    "duration": 20,
    "status": "Done",
    "author": "hellokimmydream",
    "patch": true
  },
  {
    "id": "f169cd03-dd2e-4abe-b845-2cdef4078e14",
    "type": "commitpatch",
    "sha": "c6fd7fa6df254781d1cb062f7352f96c07971097",
    "url": "https://github.com/hellokimmydream/p-bulle-exercices-js-start/commit/c6fd7fa6df254781d1cb062f7352f96c07971097",
    "name": "feat( poetry-door-policy)",
    "description": "execice terminé",
    "date": "2025-11-21T13:26:00.000Z",
    "duration": 40,
    "status": "Done",
    "author": "hellokimmydream",
    "patch": true
  },
  {
    "id": "83bac570-bb76-4c1d-8c72-4835b768df59",
    "type": "commitpatch",
    "sha": "61b54c28841ea70d75221a4435831a042d596150",
    "url": "https://github.com/hellokimmydream/p-bulle-exercices-js-start/commit/61b54c28841ea70d75221a4435831a042d596150",
    "name": "feat(elyses-enchetments)",
    "description": "terminé",
    "date": "2025-11-21T14:57:00.000Z",
    "duration": 70,
    "status": "Done",
    "author": "hellokimmydream",
    "patch": true
  },
  {
    "id": "1bb54a18-479d-4df6-b425-bf3bc80b12f1",
    "type": "commitpatch",
    "sha": "36a462a2947caf56dbc3af5eba11ab33cfa9cb66",
    "url": "https://github.com/hellokimmydream/p-bulle-exercices-js-start/commit/36a462a2947caf56dbc3af5eba11ab33cfa9cb66",
    "name": "feat( fruit-picker)",
    "description": "In progress",
    "date": "2025-11-21T15:33:00.000Z",
    "duration": 20,
    "status": "WIP",
    "author": "hellokimmydream",
    "patch": true
  },
  {
    "id": "55e6f155-c7c7-4b98-a9b7-53b4a045b203",
    "type": "commitpatch",
    "sha": "de336b14196b056760c2cbe50371aec55a432cbb",
    "url": "https://github.com/hellokimmydream/p-bulle-exercices-js-start/commit/de336b14196b056760c2cbe50371aec55a432cbb",
    "name": "feat(elyses-enchantement)",
    "description": "exercice terminé",
    "date": "2025-12-05T14:40:00.000Z",
    "duration": 40,
    "status": "Done",
    "author": "hellokimmydream",
    "patch": true
  },
  {
    "id": "3105572a-9c72-4183-a72d-95fedd946460",
    "type": "commitpatch",
    "sha": "709739f2d2bef87f63df549aa23ebb3596656e84",
    "url": "https://github.com/hellokimmydream/p-bulle-exercices-js-start/commit/709739f2d2bef87f63df549aa23ebb3596656e84",
    "name": "feat(bird-watcher)",
    "description": "Ce genre de donnée d'exercice a tendance a être une gymnastique compliqué pour moi",
    "date": "2025-12-05T16:34",
    "duration": 25,
    "status": "WIP",
    "author": "hellokimmydream",
    "patch": true
  },
  {
    "id": "294a4b28-b1bc-4eba-b560-6cb451c358a7",
    "type": "commitpatch",
    "sha": "5e3fbf0664f5648f73cf6695fde7846a220261b9",
    "url": "https://github.com/hellokimmydream/p-bulle-exercices-js-start/commit/5e3fbf0664f5648f73cf6695fde7846a220261b9",
    "name": "chore(feedback)",
    "description": "test résolution de problème",
    "date": "2026-01-09T12:53:00.000Z",
    "duration": 10,
    "status": "Done",
    "author": "hellokimmydream",
    "patch": true
  },
  {
    "id": "4264a3c3-378b-41b9-ad92-e7653cdb29ec",
    "type": "commitless",
    "name": "feat(bob)",
    "description": "regEx ok, trim() ok mais je rencontrain des probleme avec message vide depuis plusieurs semaine, test reussi avec (message) => message === \"\", avant je cherchais trop loin",
    "date": "2026-01-09T14:03:00.000Z",
    "duration": 40,
    "status": "Done"
  }
]